cognee_community_retriever_code/__init__.py
cognee_community_retriever_code/code_retriever.py
cognee_community_retriever_code/register.py
cognee_community_retriever_code-0.1.0.dist-info/METADATA
cognee_community_retriever_code-0.1.0.dist-info/WHEEL
cognee_community_retriever_code-0.1.0.dist-info/RECORD
