Metadata-Version: 2.4
Name: cognee-community-retriever-code
Version: 0.1.0
Summary: Package containing a custom cognee retriever for working with code repositories
Requires-Python: >=3.11,<=3.13
Classifier: Programming Language :: Python :: 3
Classifier: Programming Language :: Python :: 3.11
Classifier: Programming Language :: Python :: 3.12
Classifier: Programming Language :: Python :: 3.13
Requires-Dist: aenum (>=3.1.16)
Requires-Dist: cognee (==0.5.0)
